listdiffer/__init__.py
listdiffer/differ.py
listdiffer/formatter.py
listdiffer/patch_parser.py
listdiffer-0.3.0.dist-info/LICENSE
listdiffer-0.3.0.dist-info/METADATA
listdiffer-0.3.0.dist-info/WHEEL
listdiffer-0.3.0.dist-info/RECORD
