Metadata-Version: 2.3
Name: listdiffer
Version: 0.3.0
Summary: Generate diffs on lists of numbers, bytes or objects
License: MIT License
Keywords: lcs,diff,delta,patch
Author: Jacob Reimers
Author-email: pypi@reimers.io
Requires-Python: >=3.8
Classifier: License :: OSI Approved :: MIT License
Classifier: Programming Language :: Python
Classifier: Programming Language :: Python :: 3
Provides-Extra: dev
Requires-Dist: pip-tools ; extra == "dev"
Requires-Dist: pytest ; extra == "dev"
Project-URL: Homepage, https://github.com/jjrdk/listdiffer
